argcmd/__init__.py
argcmd/__main__.py
argcmd-0.1.0.dist-info/entry_points.txt
argcmd-0.1.0.dist-info/LICENSE
argcmd-0.1.0.dist-info/WHEEL
argcmd-0.1.0.dist-info/METADATA
argcmd-0.1.0.dist-info/RECORD
