Metadata-Version: 2.1
Name: argcmd
Version: 0.1.0
Summary: 
License: AGPL v3
Author: Lee Braiden
Author-email: leebraid@gmail.com
Requires-Python: >=3.7,<4.0
Classifier: License :: Other/Proprietary License
Classifier: Programming Language :: Python :: 3
Classifier: Programming Language :: Python :: 3.7
Classifier: Programming Language :: Python :: 3.8
Classifier: Programming Language :: Python :: 3.9
Classifier: Programming Language :: Python :: 3.10
